{
  "db_name": "PostgreSQL",
  "query": "\n        INSERT INTO project (project_name, project_id)\n        VALUES ($1, $2)\n        RETURNING project_id\n        ",
  "describe": {
    "columns": [
      {
        "ordinal": 0,
        "name": "project_id",
        "type_info": "Uuid"
      }
    ],
    "parameters": {
      "Left": [
        "Text",
        "Uuid"
      ]
    },
    "nullable": [
      false
    ]
  },
  "hash": "9f23e7ec362c786e9524941bf385fa4d940951bf20555d77e727b523074f33ae"
}
