{
  "db_name": "PostgreSQL",
  "query": "\n        INSERT INTO namespace (warehouse_id, \"name\", properties)\n        VALUES ($1, $2, $3)\n        RETURNING namespace_id\n        ",
  "describe": {
    "columns": [
      {
        "ordinal": 0,
        "name": "namespace_id",
        "type_info": "Uuid"
      }
    ],
    "parameters": {
      "Left": [
        "Uuid",
        "TextArray",
        "Jsonb"
      ]
    },
    "nullable": [
      false
    ]
  },
  "hash": "84cc5f0fce2b8cc595e21c6be785815c885909b5b3c60f1af83bbde30fc9fa78"
}
