{
  "db_name": "PostgreSQL",
  "query": "\n            INSERT INTO view_representation (view_version_unique_id, view_representation_id, typ, sql, dialect)\n            VALUES ($1, $2, $3, $4, $5)\n            ",
  "describe": {
    "columns": [],
    "parameters": {
      "Left": [
        "Uuid",
        "Uuid",
        {
          "Custom": {
            "name": "view_representation_type",
            "kind": {
              "Enum": [
                "sql"
              ]
            }
          }
        },
        "Text",
        "Text"
      ]
    },
    "nullable": []
  },
  "hash": "954810b1790ffdb79bbfbf33b78ff3ff67f9d1ba8925326281c08cfcdba768e9"
}
